windmillendpointv1/__init__.py
windmillendpointv1/client/__init__.py
windmillendpointv1/client/endpoint_monitor/__init__.py
windmillendpointv1/client/endpoint_monitor/endpoint_monitor_client.py
windmillendpointv1/client/endpoint_monitor/getter.py
windmillendpointv1/client/endpointv1/__init__.py
windmillendpointv1/client/endpointv1/endpoint_api.py
windmillendpointv1/client/endpointv1/endpoint_api_deploy_job.py
windmillendpointv1/client/endpointv1/endpoint_api_deployment.py
windmillendpointv1/client/endpointv1/endpoint_api_endpoint_hub.py
windmillendpointv1/client/endpointv1/endpoint_client.py
windmillendpointv1/client/gaea/__init__.py
windmillendpointv1/client/gaea/api.py
windmillendpointv1/client/gaea/example.py
windmillendpointv1/client/gaea/infer.py
windmillendpointv1-1.0.0.23.dev2.dist-info/METADATA
windmillendpointv1-1.0.0.23.dev2.dist-info/WHEEL
windmillendpointv1-1.0.0.23.dev2.dist-info/top_level.txt
windmillendpointv1-1.0.0.23.dev2.dist-info/RECORD
