Metadata-Version: 2.1
Name: windmillendpointv1
Version: 1.0.0.23.dev2
Summary: Add your description here
Requires-Python: >=3.8
Requires-Dist: bce-internal-sdk >=1.0.0.11
Requires-Dist: bce-python-sdk ==0.8.87
Requires-Dist: lmdeployv1 ~=0.0.9.1
Requires-Dist: multidict ==6.0.4
Requires-Dist: pillow >=10.4.0
Requires-Dist: tritonclient >=2.41.1
Requires-Dist: tritonv2 ~=1.2.8 ; sys_platform != "darwin"
